python_lifecycle_training/__init__.py
python_lifecycle_training/calculator/__init__.py
python_lifecycle_training/calculator/broken.py
python_lifecycle_training/calculator/cli.py
python_lifecycle_training/calculator/complex.py
python_lifecycle_training/calculator/simple.py
python_lifecycle_training-0.1.3.dist-info/entry_points.txt
python_lifecycle_training-0.1.3.dist-info/LICENSE
python_lifecycle_training-0.1.3.dist-info/WHEEL
python_lifecycle_training-0.1.3.dist-info/METADATA
python_lifecycle_training-0.1.3.dist-info/RECORD
