Metadata-Version: 2.1
Name: python-lifecycle-training
Version: 0.1.3
Summary: A training program to learn the Python Development Cycle
Home-page: https://github.com/sp-fm/python-lifecycle-training
License: MIT
Author: Shashanka Prajapati
Author-email: shashanka@fusemachines.com
Requires-Python: >=3.7,<4.0
Classifier: Development Status :: 2 - Pre-Alpha
Classifier: Intended Audience :: Developers
Classifier: License :: OSI Approved :: MIT License
Classifier: Natural Language :: English
Classifier: Programming Language :: Python :: 3
Classifier: Programming Language :: Python :: 3 :: Only
Classifier: Programming Language :: Python :: 3.7
Classifier: Programming Language :: Python :: 3.8
Classifier: Programming Language :: Python :: 3.9
Requires-Dist: dynaconf (>=3.1.2,<4.0.0)
Requires-Dist: fire (>=0.3.1,<0.4.0)
Requires-Dist: loguru (>=0.5.3,<0.6.0)
Project-URL: Bug Tracker, https://github.com/sp-fm/python-lifecycle-training/issues
Project-URL: Documentation, https://sp-fm.github.io/python-lifecycle-training/
Project-URL: Repository, https://github.com/sp-fm/python-lifecycle-training
